<!DOCTYPE flight_plan SYSTEM "../flight_plan.dtd">

<flight_plan alt="1.0" ground_alt ="0" lat0="51.990634" lon0="4.376789" max_dist_from_home="20" name="Bebop with stereo cam and Wedgebug TU Delft Cyberzoo" security_height="0.4">
  <header>
    #include "subsystems/datalink/datalink.h"
    #include "subsystems/electrical.h"
    #include "modules/radio_control/radio_control.h"
    #include "subsystems/ahrs.h"
    #define NPS_GAZEBO_WORLD "cyberzoo2019_ralphthesis2020.world" <!-- Current world is based on "cyberzoo2019_orange_poles_panels_mats.world" and replaced the original "cyberzoo_orange_poles.world" that was used here -->

#include "autopilot.h"
inline void setNav(void){
  autopilot_mode_auto2 = AP_MODE_NAV;
  autopilot_static_set_mode(AP_MODE_NAV);
}
inline void setGuided(void){
  autopilot_mode_auto2 = AP_MODE_GUIDED;
  autopilot_static_set_mode(AP_MODE_GUIDED);
}



</header>
  <waypoints>
    <!-- <waypoint lat="51.990631" lon="4.376796" name="HOME"/> -->
    <waypoint lat="51.990631" lon="4.376796" name="HOME"/>
    <waypoint name="_CLIMB" x="1.9" y="1.0"/>
    <waypoint name="_STDBY" x="1.9" y="1.0"/>
    <waypoint name="_TD" x="0.8" y="-1.7"/>
    <waypoint name="_GOAL1" x="1.9" y="1.0"/>
    <waypoint name="_TRAJECTORY" x="1.9" y="1.0"/>
    

    
    
    <waypoint  name="START" x="0.0" y="0.0" alt= "1"/>
   <!-- <waypoint  name="START2" x="2.0" y="1" alt= "1"/>-->
    <waypoint  name="GOAL" x="0.0" y="8" alt= "1"/>
    <!--  <waypoint  name="GOAL2" x="2.0" y="8" alt= "1"/>-->
    
    
    <waypoint  x="-6.0" y="-2.0" name="_CZ1"/>
    <waypoint  x="-6.0" y="10.0" name="_CZ2"/>
    <waypoint  x="5.0" y="10.0" name="_CZ3"/>
    <waypoint  x="5.0" y="-2.0" name="_CZ4"/>
    
    <waypoint  x="-5.0" y="-1.0" name="_OZ1"/>
    <waypoint  x="-5.0" y="9.0" name="_OZ2"/>
    <waypoint  x="4.0" y="9.0" name="_OZ3"/>
    <waypoint  x="4.0" y="-1.0" name="_OZ4"/>
    
    
    
    
    
  </waypoints>
  <sectors>
    <sector color="red" name="CyberZoo">
      <corner name="_CZ1"/>
      <corner name="_CZ2"/>
      <corner name="_CZ3"/>
      <corner name="_CZ4"/>
    </sector>
    <sector color="green" name="ObstacleZone">
      <corner name="_OZ1"/>
      <corner name="_OZ2"/>
      <corner name="_OZ3"/>
      <corner name="_OZ4"/>
    </sector>
    
    
  </sectors>
  <exceptions>
    <!-- RC lost -->
    <!--exception cond="((radio_control.status == RC_REALLY_LOST) @AND
      !(IndexOfBlock('Holding point') @GT nav_block) @AND
      !(nav_block >= IndexOfBlock('land here')) @AND
      (autopilot_in_flight() == true) )" deroute="Standby"/-->
    <!-- Datalink lost (constant RPM descent) -->
    <exception cond="((datalink_time @GT 5) @AND
      !(IndexOfBlock('Holding point') @GT nav_block) @AND
      !(nav_block >= IndexOfBlock('land here')) @AND
      (autopilot_in_flight() == true) )" deroute="land here"/>
    <!-- Geofencing XY -->
    <exception cond="(!InsideCyberZoo(GetPosX(), GetPosY()) @AND
      !(IndexOfBlock('Holding point') @GT nav_block) @AND
      !(nav_block >= IndexOfBlock('land here')) @AND
      (autopilot_in_flight() == true) )" deroute="land here"/>
    <!-- Geofencing Z 3.5 -->
    <exception cond="((GetPosAlt() @GT 3.5) @AND
      !(IndexOfBlock('Holding point') @GT nav_block) @AND
      !(nav_block >= IndexOfBlock('land here')) @AND
      (autopilot_in_flight() == true) )" deroute="land here"/>
    <!-- Geofencing Z 4.5 (constant RPM descent)-->
    <exception cond="((GetPosAlt() @GT 4.5) @AND
      !(IndexOfBlock('Holding point') @GT nav_block) @AND
      (autopilot_in_flight() == true) )" deroute="Landed"/>
    <!-- Bat low -->
    <exception cond="(electrical.bat_low @AND
      !(IndexOfBlock('Holding point') @GT nav_block) @AND
      !(nav_block >= IndexOfBlock('land here')) @AND
      (autopilot_in_flight() == true) )" deroute="land here"/>
    <!-- Bat critical (constant RPM no stabilization)-->
    <exception cond="(electrical.bat_critical @AND
      !(IndexOfBlock('Holding point') @GT nav_block) @AND
      !(nav_block >= IndexOfBlock('land here')) @AND
      (autopilot_in_flight() == true) )" deroute="land here"/>
  </exceptions>
  <blocks>
    <block name="Wait GPS">
      <call_once fun="NavKillThrottle()"/>
      <while cond="!GpsFixValid()"/>
    </block>
    <block name="Geo init">
      <while cond="LessThan(NavBlockTime(), 2)"/>
      <call_once fun="NavSetAltitudeReferenceHere()"/>
    </block>
    
    <!-- Mdfd: Same as "1: Initial position" --> 
    <block name="Holding point">
      <call_once fun="NavKillThrottle()"/>
      <attitude pitch="0" roll="0" throttle="0" until="FALSE" vmode="throttle"/>
    </block>
    
    <block key="r" name="Start Engine">
      <call_once fun="NavResurrect()"/>
      <attitude pitch="0" roll="0" throttle="0" until="FALSE" vmode="throttle"/>
      <call_once fun="NavResurrect()"/>
    </block>
    
    
    <block key="t" name="Takeoff" strip_button="Takeoff" strip_icon="takeoff.png">
      <exception cond="GetPosAlt() @GT 0.8" deroute="Standby"/>
      <call_once fun="NavSetWaypointHere(WP__CLIMB)"/>
      <stay climb="nav_climb_vspeed" vmode="climb" wp="_CLIMB"/>
    </block>
    
    <block key="s" name="Standby" strip_button="Standby" strip_icon="home.png">
      <call_once fun="NavSetWaypointHere(WP__STDBY)"/>
      <stay wp="_STDBY"/>
    </block>
    
    

    
    <!-- Mdfd: Same as "2: Move to start" --> 
    <block name="1 - Move to Start">
      <call_once fun="NavResurrect()"/>
      <go wp="START"/>
      <stay wp="START"/>
    </block>
    
    
    
    <block key="g" name="2 - Start Experiment" strip_button="Go" strip_icon="lookfore.png">
      <deroute block="Move to goal"/>
    </block>
    
    
    <!-- Mdfd: Same as "4: Move to goal" --> 
    <block name="Move to goal">
      <call_once fun = "set_state(1,1)"/>    
      <call_once fun="setGuided()"/>   
      <deroute block="Position goal"/>
    </block>
    
    
    <!-- Mdfd: Same as "5: Position goal" --> 
    <block name="Position goal">
      <stay wp="GOAL"/>
    </block>
    
 
    

    <block key="l" name="land here" strip_button="land here" strip_icon="land-right.png">
      <call_once fun="NavSetWaypointHere(WP__TD)"/>
      <go wp="_TD"/>
      <deroute block="Flare"/>
    </block>
    <block name="Land">
      <go wp="_TD"/>
      <deroute block="Flare"/>
    </block>
    <block name="Flare">
      <exception cond="NavDetectGround()" deroute="Holding point"/>
      <exception cond="!nav_is_in_flight()" deroute="Landed"/>
      <exception cond="0.10 @GT GetPosAlt()" deroute="Landed"/>
      <call_once fun="NavStartDetectGround()"/>
      <stay climb="nav_descend_vspeed" vmode="climb" wp="_TD"/>
    </block>
    <block name="Landed">
      <call_once fun="NavKillThrottle()"/>
      <attitude pitch="0" roll="0" throttle="0" until="FALSE" vmode="throttle"/>
    </block>
  </blocks>
</flight_plan>
